{"id":"_ast","path":"/Users/georgeskhawam/.cache/pre-commit/reposo30y02z/py_env-python3.11/lib/python3.11/site-packages/mypy/typeshed/stdlib/_ast.pyi","mtime":1751884530,"size":15576,"hash":"9200c1d4388b51588a727cd2bf6c3083fe20faf8736f81055ed1b3e172df4565","data_mtime":1751824638,"dependencies":["sys","typing_extensions","typing","builtins","_typeshed","abc","types"],"suppressed":[],"options":{"strict_concatenate":false,"disallow_untyped_calls":false,"disallow_any_expr":false,"disable_error_code":[],"extra_checks":false,"allow_redefinition":false,"warn_unused_ignores":false,"platform":"darwin","enabled_error_codes":[],"disabled_error_codes":[],"disallow_any_unimported":false,"warn_no_return":true,"disallow_subclassing_any":false,"always_false":[],"check_untyped_defs":false,"disallow_untyped_defs":false,"local_partial_types":false,"disallow_any_decorated":false,"warn_return_any":false,"ignore_errors":false,"bazel":false,"enable_error_code":[],"disallow_untyped_decorators":false,"implicit_reexport":true,"allow_untyped_globals":false,"strict_optional":true,"always_true":[],"disallow_incomplete_defs":false,"warn_unreachable":false,"mypyc":false,"disable_bytearray_promotion":false,"ignore_missing_imports":true,"disallow_any_explicit":false,"implicit_optional":false,"follow_imports_for_stubs":false,"strict_equality":false,"disable_memoryview_promotion":false,"follow_imports":"normal","plugins":[],"disallow_any_generics":false,"old_type_inference":false},"dep_prios":[10,10,5,5,30,30,30],"dep_lines":[1,2,3,1,1,1,1],"interface_hash":"077322ff224e7b2ac1af3270639aa57beb8961f6617947c02a16097572166ae4","version_id":"1.10.0","ignore_all":true,"plugin_data":null}