{".class":"MypyFile","_fullname":"mutagen.id3._util","future_import_flags":[],"is_partial_stub_package":false,"is_stub":false,"names":{".class":"SymbolTable","BitPaddedInt":{".class":"SymbolTableNode","kind":"Gdef","node":{".class":"TypeInfo","_promote":[],"abstract_attributes":[],"alt_promote":null,"bases":["builtins.int","mutagen.id3._util._BitPaddedMixin"],"dataclass_transform_spec":null,"declared_metaclass":null,"defn":{".class":"ClassDef","fullname":"mutagen.id3._util.BitPaddedInt","name":"BitPaddedInt","type_vars":[]},"deletable_attributes":[],"deprecated":null,"flags":[],"fullname":"mutagen.id3._util.BitPaddedInt","has_param_spec_type":false,"metaclass_type":null,"metadata":{},"module_name":"mutagen.id3._util","mro":["mutagen.id3._util.BitPaddedInt","builtins.int","mutagen.id3._util._BitPaddedMixin","builtins.object"],"names":{".class":"SymbolTable","__new__":{".class":"SymbolTableNode","kind":"Mdef","node":{".class":"FuncDef","abstract_status":0,"arg_kinds":[0,0,1,1],"arg_names":["cls","value","bits","bigendian"],"dataclass_transform_spec":null,"deprecated":null,"flags":["is_static"],"fullname":"mutagen.id3._util.BitPaddedInt.__new__","name":"__new__","type":null}}},"self_type":{".class":"TypeVarType","default":{".class":"AnyType","missing_import_name":null,"source_any":null,"type_of_any":4},"fullname":"mutagen.id3._util.BitPaddedInt.Self","id":0,"name":"Self","namespace":"","upper_bound":"mutagen.id3._util.BitPaddedInt","values":[],"variance":0},"slots":null,"tuple_type":null,"type_vars":[],"typeddict_type":null}},"ID3BadCompressedData":{".class":"SymbolTableNode","kind":"Gdef","node":{".class":"TypeInfo","_promote":[],"abstract_attributes":[],"alt_promote":null,"bases":["mutagen.id3._util.error","builtins.ValueError"],"dataclass_transform_spec":null,"declared_metaclass":null,"defn":{".class":"ClassDef","fullname":"mutagen.id3._util.ID3BadCompressedData","name":"ID3BadCompressedData","type_vars":[]},"deletable_attributes":[],"deprecated":null,"flags":[],"fullname":"mutagen.id3._util.ID3BadCompressedData","has_param_spec_type":false,"metaclass_type":null,"metadata":{},"module_name":"mutagen.id3._util","mro":["mutagen.id3._util.ID3BadCompressedData","mutagen.id3._util.error","mutagen._util.MutagenError","builtins.ValueError","builtins.Exception","builtins.BaseException","builtins.object"],"names":{".class":"SymbolTable"},"self_type":{".class":"TypeVarType","default":{".class":"AnyType","missing_import_name":null,"source_any":null,"type_of_any":4},"fullname":"mutagen.id3._util.ID3BadCompressedData.Self","id":0,"name":"Self","namespace":"","upper_bound":"mutagen.id3._util.ID3BadCompressedData","values":[],"variance":0},"slots":null,"tuple_type":null,"type_vars":[],"typeddict_type":null}},"ID3BadUnsynchData":{".class":"SymbolTableNode","kind":"Gdef","node":{".class":"TypeInfo","_promote":[],"abstract_attributes":[],"alt_promote":null,"bases":["mutagen.id3._util.error","builtins.ValueError"],"dataclass_transform_spec":null,"declared_metaclass":null,"defn":{".class":"ClassDef","fullname":"mutagen.id3._util.ID3BadUnsynchData","name":"ID3BadUnsynchData","type_vars":[]},"deletable_attributes":[],"deprecated":null,"flags":[],"fullname":"mutagen.id3._util.ID3BadUnsynchData","has_param_spec_type":false,"metaclass_type":null,"metadata":{},"module_name":"mutagen.id3._util","mro":["mutagen.id3._util.ID3BadUnsynchData","mutagen.id3._util.error","mutagen._util.MutagenError","builtins.ValueError","builtins.Exception","builtins.BaseException","builtins.object"],"names":{".class":"SymbolTable"},"self_type":{".class":"TypeVarType","default":{".class":"AnyType","missing_import_name":null,"source_any":null,"type_of_any":4},"fullname":"mutagen.id3._util.ID3BadUnsynchData.Self","id":0,"name":"Self","namespace":"","upper_bound":"mutagen.id3._util.ID3BadUnsynchData","values":[],"variance":0},"slots":null,"tuple_type":null,"type_vars":[],"typeddict_type":null}},"ID3EncryptionUnsupportedError":{".class":"SymbolTableNode","kind":"Gdef","node":{".class":"TypeInfo","_promote":[],"abstract_attributes":[],"alt_promote":null,"bases":["mutagen.id3._util.error","builtins.NotImplementedError"],"dataclass_transform_spec":null,"declared_metaclass":null,"defn":{".class":"ClassDef","fullname":"mutagen.id3._util.ID3EncryptionUnsupportedError","name":"ID3EncryptionUnsupportedError","type_vars":[]},"deletable_attributes":[],"deprecated":null,"flags":[],"fullname":"mutagen.id3._util.ID3EncryptionUnsupportedError","has_param_spec_type":false,"metaclass_type":null,"metadata":{},"module_name":"mutagen.id3._util","mro":["mutagen.id3._util.ID3EncryptionUnsupportedError","mutagen.id3._util.error","mutagen._util.MutagenError","builtins.NotImplementedError","builtins.RuntimeError","builtins.Exception","builtins.BaseException","builtins.object"],"names":{".class":"SymbolTable"},"self_type":{".class":"TypeVarType","default":{".class":"AnyType","missing_import_name":null,"source_any":null,"type_of_any":4},"fullname":"mutagen.id3._util.ID3EncryptionUnsupportedError.Self","id":0,"name":"Self","namespace":"","upper_bound":"mutagen.id3._util.ID3EncryptionUnsupportedError","values":[],"variance":0},"slots":null,"tuple_type":null,"type_vars":[],"typeddict_type":null}},"ID3JunkFrameError":{".class":"SymbolTableNode","kind":"Gdef","node":{".class":"TypeInfo","_promote":[],"abstract_attributes":[],"alt_promote":null,"bases":["mutagen.id3._util.error"],"dataclass_transform_spec":null,"declared_metaclass":null,"defn":{".class":"ClassDef","fullname":"mutagen.id3._util.ID3JunkFrameError","name":"ID3JunkFrameError","type_vars":[]},"deletable_attributes":[],"deprecated":null,"flags":[],"fullname":"mutagen.id3._util.ID3JunkFrameError","has_param_spec_type":false,"metaclass_type":null,"metadata":{},"module_name":"mutagen.id3._util","mro":["mutagen.id3._util.ID3JunkFrameError","mutagen.id3._util.error","mutagen._util.MutagenError","builtins.Exception","builtins.BaseException","builtins.object"],"names":{".class":"SymbolTable"},"self_type":{".class":"TypeVarType","default":{".class":"AnyType","missing_import_name":null,"source_any":null,"type_of_any":4},"fullname":"mutagen.id3._util.ID3JunkFrameError.Self","id":0,"name":"Self","namespace":"","upper_bound":"mutagen.id3._util.ID3JunkFrameError","values":[],"variance":0},"slots":null,"tuple_type":null,"type_vars":[],"typeddict_type":null}},"ID3NoHeaderError":{".class":"SymbolTableNode","kind":"Gdef","node":{".class":"TypeInfo","_promote":[],"abstract_attributes":[],"alt_promote":null,"bases":["mutagen.id3._util.error","builtins.ValueError"],"dataclass_transform_spec":null,"declared_metaclass":null,"defn":{".class":"ClassDef","fullname":"mutagen.id3._util.ID3NoHeaderError","name":"ID3NoHeaderError","type_vars":[]},"deletable_attributes":[],"deprecated":null,"flags":[],"fullname":"mutagen.id3._util.ID3NoHeaderError","has_param_spec_type":false,"metaclass_type":null,"metadata":{},"module_name":"mutagen.id3._util","mro":["mutagen.id3._util.ID3NoHeaderError","mutagen.id3._util.error","mutagen._util.MutagenError","builtins.ValueError","builtins.Exception","builtins.BaseException","builtins.object"],"names":{".class":"SymbolTable"},"self_type":{".class":"TypeVarType","default":{".class":"AnyType","missing_import_name":null,"source_any":null,"type_of_any":4},"fullname":"mutagen.id3._util.ID3NoHeaderError.Self","id":0,"name":"Self","namespace":"","upper_bound":"mutagen.id3._util.ID3NoHeaderError","values":[],"variance":0},"slots":null,"tuple_type":null,"type_vars":[],"typeddict_type":null}},"ID3SaveConfig":{".class":"SymbolTableNode","kind":"Gdef","node":{".class":"TypeInfo","_promote":[],"abstract_attributes":[],"alt_promote":null,"bases":["builtins.object"],"dataclass_transform_spec":null,"declared_metaclass":null,"defn":{".class":"ClassDef","fullname":"mutagen.id3._util.ID3SaveConfig","name":"ID3SaveConfig","type_vars":[]},"deletable_attributes":[],"deprecated":null,"flags":[],"fullname":"mutagen.id3._util.ID3SaveConfig","has_param_spec_type":false,"metaclass_type":null,"metadata":{},"module_name":"mutagen.id3._util","mro":["mutagen.id3._util.ID3SaveConfig","builtins.object"],"names":{".class":"SymbolTable","__init__":{".class":"SymbolTableNode","kind":"Mdef","node":{".class":"FuncDef","abstract_status":0,"arg_kinds":[0,1,1],"arg_names":["self","v2_version","v23_separator"],"dataclass_transform_spec":null,"deprecated":null,"flags":[],"fullname":"mutagen.id3._util.ID3SaveConfig.__init__","name":"__init__","type":null}},"v23_separator":{".class":"SymbolTableNode","implicit":true,"kind":"Mdef","node":{".class":"Var","flags":["is_inferred"],"fullname":"mutagen.id3._util.ID3SaveConfig.v23_separator","name":"v23_separator","setter_type":null,"type":{".class":"AnyType","missing_import_name":null,"source_any":null,"type_of_any":1}}},"v2_version":{".class":"SymbolTableNode","implicit":true,"kind":"Mdef","node":{".class":"Var","flags":["is_inferred"],"fullname":"mutagen.id3._util.ID3SaveConfig.v2_version","name":"v2_version","setter_type":null,"type":{".class":"AnyType","missing_import_name":null,"source_any":null,"type_of_any":1}}}},"self_type":{".class":"TypeVarType","default":{".class":"AnyType","missing_import_name":null,"source_any":null,"type_of_any":4},"fullname":"mutagen.id3._util.ID3SaveConfig.Self","id":0,"name":"Self","namespace":"","upper_bound":"mutagen.id3._util.ID3SaveConfig","values":[],"variance":0},"slots":null,"tuple_type":null,"type_vars":[],"typeddict_type":null}},"ID3TagError":{".class":"SymbolTableNode","kind":"Gdef","node":{".class":"TypeInfo","_promote":[],"abstract_attributes":[],"alt_promote":null,"bases":["mutagen.id3._util.error","builtins.ValueError"],"dataclass_transform_spec":null,"declared_metaclass":null,"defn":{".class":"ClassDef","fullname":"mutagen.id3._util.ID3TagError","name":"ID3TagError","type_vars":[]},"deletable_attributes":[],"deprecated":null,"flags":[],"fullname":"mutagen.id3._util.ID3TagError","has_param_spec_type":false,"metaclass_type":null,"metadata":{},"module_name":"mutagen.id3._util","mro":["mutagen.id3._util.ID3TagError","mutagen.id3._util.error","mutagen._util.MutagenError","builtins.ValueError","builtins.Exception","builtins.BaseException","builtins.object"],"names":{".class":"SymbolTable"},"self_type":{".class":"TypeVarType","default":{".class":"AnyType","missing_import_name":null,"source_any":null,"type_of_any":4},"fullname":"mutagen.id3._util.ID3TagError.Self","id":0,"name":"Self","namespace":"","upper_bound":"mutagen.id3._util.ID3TagError","values":[],"variance":0},"slots":null,"tuple_type":null,"type_vars":[],"typeddict_type":null}},"ID3UnsupportedVersionError":{".class":"SymbolTableNode","kind":"Gdef","node":{".class":"TypeInfo","_promote":[],"abstract_attributes":[],"alt_promote":null,"bases":["mutagen.id3._util.error","builtins.NotImplementedError"],"dataclass_transform_spec":null,"declared_metaclass":null,"defn":{".class":"ClassDef","fullname":"mutagen.id3._util.ID3UnsupportedVersionError","name":"ID3UnsupportedVersionError","type_vars":[]},"deletable_attributes":[],"deprecated":null,"flags":[],"fullname":"mutagen.id3._util.ID3UnsupportedVersionError","has_param_spec_type":false,"metaclass_type":null,"metadata":{},"module_name":"mutagen.id3._util","mro":["mutagen.id3._util.ID3UnsupportedVersionError","mutagen.id3._util.error","mutagen._util.MutagenError","builtins.NotImplementedError","builtins.RuntimeError","builtins.Exception","builtins.BaseException","builtins.object"],"names":{".class":"SymbolTable"},"self_type":{".class":"TypeVarType","default":{".class":"AnyType","missing_import_name":null,"source_any":null,"type_of_any":4},"fullname":"mutagen.id3._util.ID3UnsupportedVersionError.Self","id":0,"name":"Self","namespace":"","upper_bound":"mutagen.id3._util.ID3UnsupportedVersionError","values":[],"variance":0},"slots":null,"tuple_type":null,"type_vars":[],"typeddict_type":null}},"ID3Warning":{".class":"SymbolTableNode","kind":"Gdef","node":{".class":"TypeInfo","_promote":[],"abstract_attributes":[],"alt_promote":null,"bases":["mutagen.id3._util.error","builtins.UserWarning"],"dataclass_transform_spec":null,"declared_metaclass":null,"defn":{".class":"ClassDef","fullname":"mutagen.id3._util.ID3Warning","name":"ID3Warning","type_vars":[]},"deletable_attributes":[],"deprecated":null,"flags":[],"fullname":"mutagen.id3._util.ID3Warning","has_param_spec_type":false,"metaclass_type":null,"metadata":{},"module_name":"mutagen.id3._util","mro":["mutagen.id3._util.ID3Warning","mutagen.id3._util.error","mutagen._util.MutagenError","builtins.UserWarning","builtins.Warning","builtins.Exception","builtins.BaseException","builtins.object"],"names":{".class":"SymbolTable"},"self_type":{".class":"TypeVarType","default":{".class":"AnyType","missing_import_name":null,"source_any":null,"type_of_any":4},"fullname":"mutagen.id3._util.ID3Warning.Self","id":0,"name":"Self","namespace":"","upper_bound":"mutagen.id3._util.ID3Warning","values":[],"variance":0},"slots":null,"tuple_type":null,"type_vars":[],"typeddict_type":null}},"MutagenError":{".class":"SymbolTableNode","cross_ref":"mutagen._util.MutagenError","kind":"Gdef"},"Union":{".class":"SymbolTableNode","cross_ref":"typing.Union","kind":"Gdef"},"_BitPaddedMixin":{".class":"SymbolTableNode","kind":"Gdef","node":{".class":"TypeInfo","_promote":[],"abstract_attributes":[],"alt_promote":null,"bases":["builtins.object"],"dataclass_transform_spec":null,"declared_metaclass":null,"defn":{".class":"ClassDef","fullname":"mutagen.id3._util._BitPaddedMixin","name":"_BitPaddedMixin","type_vars":[]},"deletable_attributes":[],"deprecated":null,"flags":[],"fullname":"mutagen.id3._util._BitPaddedMixin","has_param_spec_type":false,"metaclass_type":null,"metadata":{},"module_name":"mutagen.id3._util","mro":["mutagen.id3._util._BitPaddedMixin","builtins.object"],"names":{".class":"SymbolTable","as_str":{".class":"SymbolTableNode","kind":"Mdef","node":{".class":"FuncDef","abstract_status":0,"arg_kinds":[0,1,1],"arg_names":["self","width","minwidth"],"dataclass_transform_spec":null,"deprecated":null,"flags":[],"fullname":"mutagen.id3._util._BitPaddedMixin.as_str","name":"as_str","type":null}},"has_valid_padding":{".class":"SymbolTableNode","kind":"Mdef","node":{".class":"Decorator","func":{".class":"FuncDef","abstract_status":0,"arg_kinds":[0,1],"arg_names":["value","bits"],"dataclass_transform_spec":null,"deprecated":null,"flags":["is_static","is_decorated"],"fullname":"mutagen.id3._util._BitPaddedMixin.has_valid_padding","name":"has_valid_padding","type":{".class":"CallableType","arg_kinds":[0,1],"arg_names":["value","bits"],"arg_types":[{".class":"UnionType","items":["builtins.int","builtins.bytes"],"uses_pep604_syntax":false},"builtins.int"],"def_extras":{"first_arg":null},"fallback":"builtins.function","from_concatenate":false,"implicit":false,"imprecise_arg_kinds":false,"is_bound":false,"is_ellipsis_args":false,"name":"has_valid_padding of _BitPaddedMixin","ret_type":"builtins.bool","type_guard":null,"type_is":null,"unpack_kwargs":false,"variables":[]}},"is_overload":false,"var":{".class":"Var","flags":["is_initialized_in_class","is_staticmethod","is_ready","is_inferred"],"fullname":"mutagen.id3._util._BitPaddedMixin.has_valid_padding","name":"has_valid_padding","setter_type":null,"type":{".class":"CallableType","arg_kinds":[0,1],"arg_names":["value","bits"],"arg_types":[{".class":"UnionType","items":["builtins.int","builtins.bytes"],"uses_pep604_syntax":false},"builtins.int"],"def_extras":{"first_arg":null},"fallback":"builtins.function","from_concatenate":false,"implicit":false,"imprecise_arg_kinds":false,"is_bound":false,"is_ellipsis_args":false,"name":"has_valid_padding of _BitPaddedMixin","ret_type":"builtins.bool","type_guard":null,"type_is":null,"unpack_kwargs":false,"variables":[]}}}},"to_str":{".class":"SymbolTableNode","kind":"Mdef","node":{".class":"Decorator","func":{".class":"FuncDef","abstract_status":0,"arg_kinds":[0,1,1,1,1],"arg_names":["value","bits","bigendian","width","minwidth"],"dataclass_transform_spec":null,"deprecated":null,"flags":["is_static","is_decorated"],"fullname":"mutagen.id3._util._BitPaddedMixin.to_str","name":"to_str","type":{".class":"CallableType","arg_kinds":[0,1,1,1,1],"arg_names":["value","bits","bigendian","width","minwidth"],"arg_types":["builtins.int","builtins.int","builtins.bool","builtins.int","builtins.int"],"def_extras":{"first_arg":null},"fallback":"builtins.function","from_concatenate":false,"implicit":false,"imprecise_arg_kinds":false,"is_bound":false,"is_ellipsis_args":false,"name":"to_str of _BitPaddedMixin","ret_type":"builtins.bytes","type_guard":null,"type_is":null,"unpack_kwargs":false,"variables":[]}},"is_overload":false,"var":{".class":"Var","flags":["is_initialized_in_class","is_staticmethod","is_ready","is_inferred"],"fullname":"mutagen.id3._util._BitPaddedMixin.to_str","name":"to_str","setter_type":null,"type":{".class":"CallableType","arg_kinds":[0,1,1,1,1],"arg_names":["value","bits","bigendian","width","minwidth"],"arg_types":["builtins.int","builtins.int","builtins.bool","builtins.int","builtins.int"],"def_extras":{"first_arg":null},"fallback":"builtins.function","from_concatenate":false,"implicit":false,"imprecise_arg_kinds":false,"is_bound":false,"is_ellipsis_args":false,"name":"to_str of _BitPaddedMixin","ret_type":"builtins.bytes","type_guard":null,"type_is":null,"unpack_kwargs":false,"variables":[]}}}}},"self_type":{".class":"TypeVarType","default":{".class":"AnyType","missing_import_name":null,"source_any":null,"type_of_any":4},"fullname":"mutagen.id3._util._BitPaddedMixin.Self","id":0,"name":"Self","namespace":"","upper_bound":"mutagen.id3._util._BitPaddedMixin","values":[],"variance":0},"slots":null,"tuple_type":null,"type_vars":[],"typeddict_type":null}},"__annotations__":{".class":"SymbolTableNode","kind":"Gdef","node":{".class":"Var","flags":["is_ready"],"fullname":"mutagen.id3._util.__annotations__","name":"__annotations__","setter_type":null,"type":{".class":"Instance","args":["builtins.str",{".class":"AnyType","missing_import_name":null,"source_any":null,"type_of_any":6}],"extra_attrs":null,"type_ref":"builtins.dict"}}},"__doc__":{".class":"SymbolTableNode","kind":"Gdef","node":{".class":"Var","flags":["is_ready"],"fullname":"mutagen.id3._util.__doc__","name":"__doc__","setter_type":null,"type":"builtins.str"}},"__file__":{".class":"SymbolTableNode","kind":"Gdef","node":{".class":"Var","flags":["is_ready"],"fullname":"mutagen.id3._util.__file__","name":"__file__","setter_type":null,"type":"builtins.str"}},"__name__":{".class":"SymbolTableNode","kind":"Gdef","node":{".class":"Var","flags":["is_ready"],"fullname":"mutagen.id3._util.__name__","name":"__name__","setter_type":null,"type":"builtins.str"}},"__package__":{".class":"SymbolTableNode","kind":"Gdef","node":{".class":"Var","flags":["is_ready"],"fullname":"mutagen.id3._util.__package__","name":"__package__","setter_type":null,"type":"builtins.str"}},"__spec__":{".class":"SymbolTableNode","kind":"Gdef","node":{".class":"Var","flags":["is_ready"],"fullname":"mutagen.id3._util.__spec__","name":"__spec__","setter_type":null,"type":"_frozen_importlib.ModuleSpec"}},"error":{".class":"SymbolTableNode","kind":"Gdef","node":{".class":"TypeInfo","_promote":[],"abstract_attributes":[],"alt_promote":null,"bases":["mutagen._util.MutagenError"],"dataclass_transform_spec":null,"declared_metaclass":null,"defn":{".class":"ClassDef","fullname":"mutagen.id3._util.error","name":"error","type_vars":[]},"deletable_attributes":[],"deprecated":null,"flags":[],"fullname":"mutagen.id3._util.error","has_param_spec_type":false,"metaclass_type":null,"metadata":{},"module_name":"mutagen.id3._util","mro":["mutagen.id3._util.error","mutagen._util.MutagenError","builtins.Exception","builtins.BaseException","builtins.object"],"names":{".class":"SymbolTable"},"self_type":{".class":"TypeVarType","default":{".class":"AnyType","missing_import_name":null,"source_any":null,"type_of_any":4},"fullname":"mutagen.id3._util.error.Self","id":0,"name":"Self","namespace":"","upper_bound":"mutagen.id3._util.error","values":[],"variance":0},"slots":null,"tuple_type":null,"type_vars":[],"typeddict_type":null}},"is_valid_frame_id":{".class":"SymbolTableNode","kind":"Gdef","node":{".class":"FuncDef","abstract_status":0,"arg_kinds":[0],"arg_names":["frame_id"],"dataclass_transform_spec":null,"deprecated":null,"flags":[],"fullname":"mutagen.id3._util.is_valid_frame_id","name":"is_valid_frame_id","type":null}},"unsynch":{".class":"SymbolTableNode","kind":"Gdef","node":{".class":"TypeInfo","_promote":[],"abstract_attributes":[],"alt_promote":null,"bases":["builtins.object"],"dataclass_transform_spec":null,"declared_metaclass":null,"defn":{".class":"ClassDef","fullname":"mutagen.id3._util.unsynch","name":"unsynch","type_vars":[]},"deletable_attributes":[],"deprecated":null,"flags":[],"fullname":"mutagen.id3._util.unsynch","has_param_spec_type":false,"metaclass_type":null,"metadata":{},"module_name":"mutagen.id3._util","mro":["mutagen.id3._util.unsynch","builtins.object"],"names":{".class":"SymbolTable","decode":{".class":"SymbolTableNode","kind":"Mdef","node":{".class":"Decorator","func":{".class":"FuncDef","abstract_status":0,"arg_kinds":[0],"arg_names":["value"],"dataclass_transform_spec":null,"deprecated":null,"flags":["is_static","is_decorated"],"fullname":"mutagen.id3._util.unsynch.decode","name":"decode","type":{".class":"CallableType","arg_kinds":[0],"arg_names":["value"],"arg_types":["builtins.bytes"],"def_extras":{"first_arg":null},"fallback":"builtins.function","from_concatenate":false,"implicit":false,"imprecise_arg_kinds":false,"is_bound":false,"is_ellipsis_args":false,"name":"decode of unsynch","ret_type":"builtins.bytes","type_guard":null,"type_is":null,"unpack_kwargs":false,"variables":[]}},"is_overload":false,"var":{".class":"Var","flags":["is_initialized_in_class","is_staticmethod","is_ready","is_inferred"],"fullname":"mutagen.id3._util.unsynch.decode","name":"decode","setter_type":null,"type":{".class":"CallableType","arg_kinds":[0],"arg_names":["value"],"arg_types":["builtins.bytes"],"def_extras":{"first_arg":null},"fallback":"builtins.function","from_concatenate":false,"implicit":false,"imprecise_arg_kinds":false,"is_bound":false,"is_ellipsis_args":false,"name":"decode of unsynch","ret_type":"builtins.bytes","type_guard":null,"type_is":null,"unpack_kwargs":false,"variables":[]}}}},"encode":{".class":"SymbolTableNode","kind":"Mdef","node":{".class":"Decorator","func":{".class":"FuncDef","abstract_status":0,"arg_kinds":[0],"arg_names":["value"],"dataclass_transform_spec":null,"deprecated":null,"flags":["is_static","is_decorated"],"fullname":"mutagen.id3._util.unsynch.encode","name":"encode","type":{".class":"CallableType","arg_kinds":[0],"arg_names":["value"],"arg_types":["builtins.bytes"],"def_extras":{"first_arg":null},"fallback":"builtins.function","from_concatenate":false,"implicit":false,"imprecise_arg_kinds":false,"is_bound":false,"is_ellipsis_args":false,"name":"encode of unsynch","ret_type":"builtins.bytes","type_guard":null,"type_is":null,"unpack_kwargs":false,"variables":[]}},"is_overload":false,"var":{".class":"Var","flags":["is_initialized_in_class","is_staticmethod","is_ready","is_inferred"],"fullname":"mutagen.id3._util.unsynch.encode","name":"encode","setter_type":null,"type":{".class":"CallableType","arg_kinds":[0],"arg_names":["value"],"arg_types":["builtins.bytes"],"def_extras":{"first_arg":null},"fallback":"builtins.function","from_concatenate":false,"implicit":false,"imprecise_arg_kinds":false,"is_bound":false,"is_ellipsis_args":false,"name":"encode of unsynch","ret_type":"builtins.bytes","type_guard":null,"type_is":null,"unpack_kwargs":false,"variables":[]}}}}},"self_type":{".class":"TypeVarType","default":{".class":"AnyType","missing_import_name":null,"source_any":null,"type_of_any":4},"fullname":"mutagen.id3._util.unsynch.Self","id":0,"name":"Self","namespace":"","upper_bound":"mutagen.id3._util.unsynch","values":[],"variance":0},"slots":null,"tuple_type":null,"type_vars":[],"typeddict_type":null}}},"path":"/Users/georgeskhawam/dev/flaccid/.venv/lib/python3.11/site-packages/mutagen/id3/_util.py"}